bmcook/__init__.py
bmcook/store.py
bmcook/trainer.py
bmcook/distilling/__init__.py
bmcook/moe/__init__.py
bmcook/pruning/__init__.py
bmcook/pruning/prune_func.py
bmcook/pruning/sprune/__init__.py
bmcook/pruning/sprune/do_prune.py
bmcook/pruning/sprune/engine.py
bmcook/pruning/sprune/func.py
bmcook/pruning/sprune/plugin.py
bmcook/pruning/sprune/utils.py
bmcook/quant/__init__.py
bmcook/utils/__init__.py
bmcook/utils/arguments.py
bmcook/utils/config.py
bmcook-0.1.1.1.dist-info/LICENSE
bmcook-0.1.1.1.dist-info/METADATA
bmcook-0.1.1.1.dist-info/WHEEL
bmcook-0.1.1.1.dist-info/top_level.txt
bmcook-0.1.1.1.dist-info/RECORD
