Metadata-Version: 2.1
Name: bmcook
Version: 0.1.1.1
Summary: Model Compression for Big Models
Home-page: https://github.com/OpenBMB/BMCook
Author: Baitao Gong
Author-email: gongbaitao11@gmail.com
License: Apache 2.0
License-File: LICENSE
Requires-Dist: bmtrain
Requires-Dist: model-center
